sqqueue/__init__.py
sqqueue/config.py
sqqueue/exceptions.py
sqqueue/queue.py
sqqueue/result.py
sqqueue/uuid7.py
tests/__init__.py
tests/test_queue.py
tests/test_result.py
sqqueue-0.1.0.dist-info/METADATA
sqqueue-0.1.0.dist-info/WHEEL
sqqueue-0.1.0.dist-info/top_level.txt
sqqueue-0.1.0.dist-info/RECORD
