Metadata-Version: 2.1
Name: sqqueue
Version: 0.1.0
Summary: A SQLite-based persistent queue implementation.
Home-page: https://github.com/jaymd/sqqueue
Author: James AMD
Author-email: ***@example.com
Classifier: Programming Language :: Python :: 3
Classifier: Operating System :: OS Independent
Requires-Python: >=3.7
Requires-Dist: statsd >=3.3.0 ; extra == "statsd"
Provides-Extra: dev
Requires-Dist: pre-commit ; extra == 'dev'
Requires-Dist: pytest ; extra == 'dev'
Requires-Dist: pytest-mock ; extra == 'dev'
Requires-Dist: ruff ; extra == 'dev'
Requires-Dist: black ; extra == 'dev'
Requires-Dist: isort ; extra == 'dev'
Requires-Dist: twine ; extra == 'dev'
Requires-Dist: statsd ; extra == 'dev'
